Ingres_STT/__init__.py
ingres_stt-0.1.dist-info/METADATA
ingres_stt-0.1.dist-info/WHEEL
ingres_stt-0.1.dist-info/top_level.txt
ingres_stt-0.1.dist-info/RECORD
